.coveragerc
.gitignore
.readthedocs.yml
.style.yapf
.travis.yml
CHEATSHEET.rst
LICENSE
LICENSE.APACHE2
LICENSE.MIT
MANIFEST.in
Makefile
README.rst
mktag
pyproject.toml
setup.cfg
setup.py
ci/rtd-requirements.txt
ci/test-requirements.txt
ci/travis.sh
debian/.gitignore
debian/changelog
debian/compat
debian/control
debian/rules
debian/watch
debian/source/format
docs/Makefile
docs/make.bat
docs/source/conf.py
docs/source/history.rst
docs/source/index.rst
docs/source/intro.rst
docs/source/_static/.gitkeep
examples/cleanup_bridges.py
examples/example.py
examples/originate_example.py
examples/basic/bridge_example.py
examples/basic/example.py
examples/basic/originate_example.py
examples/basic/playback_example.py
newsfragments/.gitkeep
newsfragments/README.rst
tests/__init__.py
tests/conftest.py
tests/test_example.py
trio_ari/__init__.py
trio_ari/client.py
trio_ari/model.py
trio_ari/state.py
trio_ari/util.py
trio_ari.egg-info/PKG-INFO
trio_ari.egg-info/SOURCES.txt
trio_ari.egg-info/dependency_links.txt
trio_ari.egg-info/requires.txt
trio_ari.egg-info/top_level.txt