Metadata-Version: 1.2
Name: trio-ari
Version: 0.2.9
Summary: A Trio-ified adapter for the Asterisk ARI interface
Home-page: https://github.com/M-o-a-T/trio-ari
Author: Matthias Urlichs
Author-email: matthias@urlichs.de
License: MIT -or- Apache License 2.0
Keywords: asterisk
Platform: UNKNOWN
Classifier: License :: OSI Approved :: MIT License
Classifier: License :: OSI Approved :: Apache Software License
Classifier: Operating System :: POSIX :: Linux
Classifier: Operating System :: MacOS :: MacOS X
Classifier: Programming Language :: Python :: 3 :: Only
Classifier: Programming Language :: Python :: Implementation :: CPython
Classifier: Programming Language :: Python :: Implementation :: PyPy
Classifier: Framework :: Trio
Classifier: Topic :: Communications :: Telephony
Classifier: Development Status :: 3 - Alpha
Requires-Python: >=3.6
